pymeasuremap/__init__.py
pymeasuremap/base.py
pymeasuremap/cli.py
pymeasuremap/compare.py
pymeasuremap/extract.py
pymeasuremap/utils.py
pyMeasureMap-0.1.dist-info/LICENSE.txt
pyMeasureMap-0.1.dist-info/METADATA
pyMeasureMap-0.1.dist-info/WHEEL
pyMeasureMap-0.1.dist-info/entry_points.txt
pyMeasureMap-0.1.dist-info/top_level.txt
pyMeasureMap-0.1.dist-info/RECORD
