Metadata-Version: 2.1
Name: pyMeasureMap
Version: 0.1
Summary: Python implementation of the MeasureMap specification
Home-page: https://github.com/measure-map/pyMeasureMap
Author: Johannes Hentschel
Author-email: johannes.hentschel@epfl.ch
License: CC BY-SA 4.0
Project-URL: Documentation, https://pyscaffold.org/
Platform: any
Classifier: Development Status :: 4 - Beta
Classifier: Programming Language :: Python
Requires-Python: >=3.10
License-File: LICENSE.txt
Requires-Dist: music21
Provides-Extra: dev
Requires-Dist: pymeasuremap[testing] ; extra == 'dev'
Requires-Dist: pre-commit ; extra == 'dev'
Provides-Extra: testing
Requires-Dist: setuptools ; extra == 'testing'
Requires-Dist: pytest ; extra == 'testing'
Requires-Dist: pytest-cov ; extra == 'testing'
Requires-Dist: tox ; extra == 'testing'
Requires-Dist: GitPython ; extra == 'testing'
